LICENSE
MANIFEST.in
README.rst
setup.py
django_psql_estimate.egg-info/PKG-INFO
django_psql_estimate.egg-info/SOURCES.txt
django_psql_estimate.egg-info/dependency_links.txt
django_psql_estimate.egg-info/top_level.txt
docs/.gitignore
psql_estimate/__init__.py