Metadata-Version: 1.1
Name: django-psql-estimate
Version: 0.1
Summary: Estimate expensive COUNTs on postgres
Home-page: http://github.com/czartur/django-psql-estimate
Author: Artur Czepiel
Author-email: czepiel.artur@gmail.com
License: MIT License
Platform: UNKNOWN
Classifier: Environment :: Web Environment
Classifier: Framework :: Django
Classifier: Intended Audience :: Developers
Classifier: License :: OSI Approved :: MIT License
Classifier: Operating System :: OS Independent
Classifier: Programming Language :: Python
Classifier: Programming Language :: Python :: 2
Classifier: Programming Language :: Python :: 3
